k8srad/__init__.py
k8srad/blueprint.py
k8srad/config.py
k8srad/models.py
k8srad/server.py
k8srad/views.py
k8srad/sqls/sql.py
k8srad/static/img/favicon.png
k8srad-1.0.7.dist-info/LICENSE
k8srad-1.0.7.dist-info/METADATA
k8srad-1.0.7.dist-info/WHEEL
k8srad-1.0.7.dist-info/entry_points.txt
k8srad-1.0.7.dist-info/top_level.txt
k8srad-1.0.7.dist-info/RECORD
